tinydatabase/__init__.py
tinydatabase-0.1.0.dist-info/LICENSE
tinydatabase-0.1.0.dist-info/METADATA
tinydatabase-0.1.0.dist-info/WHEEL
tinydatabase-0.1.0.dist-info/top_level.txt
tinydatabase-0.1.0.dist-info/RECORD
